fpdc_client/__init__.py
fpdc_client/auth.py
fpdc_client/base.py
fpdc_client/endpoints.py
fpdc_client/pagination.py
fpdc_client-0.2.dist-info/LICENSE
fpdc_client-0.2.dist-info/METADATA
fpdc_client-0.2.dist-info/WHEEL
fpdc_client-0.2.dist-info/top_level.txt
fpdc_client-0.2.dist-info/RECORD
