Metadata-Version: 2.1
Name: fpdc-client
Version: 0.2
Summary: Client library for FPDC
Home-page: https://github.com/fedora-infra/fpdc-client
Maintainer: Fedora Infrastructure Team
Maintainer-email: infrastructure@lists.fedoraproject.org
License: GPLv3+
Keywords: fedora
Platform: Fedora
Platform: GNU/Linux
Classifier: Development Status :: 4 - Beta
Classifier: License :: OSI Approved :: GNU General Public License v3 or later (GPLv3+)
Classifier: Operating System :: POSIX :: Linux
Classifier: Programming Language :: Python :: 3
Classifier: Programming Language :: Python :: 3.4
Classifier: Programming Language :: Python :: 3.5
Classifier: Programming Language :: Python :: 3.6
Classifier: Programming Language :: Python :: 3.7
Requires-Dist: coreapi
Requires-Dist: python-fedora
